{
    "date": "2025-05-12",
    "product_title": "2022 GMC 1500 regular cab",
    "product_price": 36900,
    "vehicle_info": {
        "mileage": 19578,
        "fuel_type": "Automatic transmission",
        "interior_color": "Black",
        "exterior_color": "White",
        "title": "Clean"
    },
    "publication_info": {
        "publication_id": 1073627654634106,
        "publication_date": "2025-05-12",
        "product_title": "2022 GMC 1500 regular cab",
        "product_price": 36900,
        "publication_description": "Clean CarFax\n1 Owner ",
        "publication_link": "https://www.facebook.com/marketplace/item/1073627654634106/",
        "publication_location": "Paterson, NJ",
        "images": [
            "https://scontent-mia3-1.xx.fbcdn.net/v/t39.30808-6/496670130_1221007549431982_1687481560361349747_n.jpg?stp=dst-jpg_s960x960_tt6&_nc_cat=106&ccb=1-7&_nc_sid=454cf4&_nc_ohc=JVkjBmRFrbsQ7kNvwEI7ml_&_nc_oc=AdkJCMvBxreclxL0uYrgCw_6d53hMqjN3jxr_jym54nQhr0_4t_tX8tlqCkfeszuBws&_nc_zt=23&_nc_ht=scontent-mia3-1.xx&_nc_gid=fZ6gu5DgcpsEfsFRFVSqtQ&oh=00_AfK7ucz_D36lYVOeICZqByou31yX60KZ5RGGl55OiLIHFg&oe=6827CC4A",
            "https://scontent-mia3-1.xx.fbcdn.net/v/t39.30808-6/496670130_1221007549431982_1687481560361349747_n.jpg?stp=dst-jpg_s960x960_tt6&_nc_cat=106&ccb=1-7&_nc_sid=454cf4&_nc_ohc=JVkjBmRFrbsQ7kNvwEI7ml_&_nc_oc=AdkJCMvBxreclxL0uYrgCw_6d53hMqjN3jxr_jym54nQhr0_4t_tX8tlqCkfeszuBws&_nc_zt=23&_nc_ht=scontent-mia3-1.xx&_nc_gid=fZ6gu5DgcpsEfsFRFVSqtQ&oh=00_AfK7ucz_D36lYVOeICZqByou31yX60KZ5RGGl55OiLIHFg&oe=6827CC4A",
            "https://scontent-mia5-1.xx.fbcdn.net/v/t39.30808-6/496921398_1221003139432423_5677420518362704390_n.jpg?stp=dst-jpg_s960x960_tt6&_nc_cat=101&ccb=1-7&_nc_sid=946e27&_nc_ohc=vdnc6mD9Z5EQ7kNvwESy4xw&_nc_oc=AdnysiH0jQfvs3xjNZPMVukMZX8shfyyhR9EgpyonqSouMRYBGOkt4mKc7QEuvWmggg&_nc_zt=23&_nc_ht=scontent-mia5-1.xx&_nc_gid=fZ6gu5DgcpsEfsFRFVSqtQ&oh=00_AfKkur0nJy_TvrtjfimB4hRlUR-3NGnCvUnivzqAhgJYyw&oe=6827C507"
        ]
    },
    "profile_info": {
        "profile_id": 100045682462392,
        "profile_name": "Josh Rosario",
        "is_dealership": true,
        "lives_in": "N/A",
        "joined_facebook_in": 2020,
        "car_listings": 12,
        "rating": "N/A",
        "ratings_number": "N/A",
        "profile_link": "https://www.facebook.com/marketplace/profile/100045682462392/"
    }
}