{
    "date": "2025-05-06",
    "product_title": "2017 Yamaha yzf-r1",
    "product_price": 14000,
    "vehicle_info": {
        "mileage": 3172,
        "fuel_type": "Manual transmission",
        "interior_color": "",
        "exterior_color": "Black"
    },
    "publication_info": {
        "publication_id": 1320294019076326,
        "publication_date": "2025-05-06",
        "product_title": "2017 Yamaha yzf-r1",
        "product_price": 14000,
        "publication_description": "2017 YAMAHA R6 TRACK READY WITH TITLE\n3172 miles\n\nYes it\u2019s been down, once, turn 3 (slow) at NYST going reverse layout (lowside on left side), 4 years ago\u2026 only bodywork and slight emotional damage. \n\nEverything working and running perfectly. \n\nReason for selling: I\u2019m a young entrepreneur starting a new business in this very inexpensive and uncorrupt economy. Negotiable to an extent.\n\nI have to sell everything in this listing together (full bike, fast Frank quick change, and OEM bodywork).  Pitbull stands not included\n\nPlease let me know if you have any questions, etc. Looking to sell ASAP. \n\nPARTS LIST IN PHOTOS See less",
        "publication_link": "https://www.facebook.com/marketplace/item/1320294019076326/",
        "publication_location": "New York, NY",
        "images": [
            "https://scontent-mia3-3.xx.fbcdn.net/v/t39.30808-6/495696638_10236806508159742_6339745641320157910_n.jpg?stp=dst-jpg_s960x960_tt6&_nc_cat=108&ccb=1-7&_nc_sid=454cf4&_nc_ohc=eCMn7Voou2MQ7kNvwE0CVZX&_nc_oc=Adn5DJMpZSTR6Uq8JEUfYte-p3qBeaqicGK_aNTVDUEi4FxVX_g69EUtMEes7zJHc_s&_nc_zt=23&_nc_ht=scontent-mia3-3.xx&_nc_gid=DsTKVZHDiKbqG7R2lPOUcg&oh=00_AfKLq9nYrAnILYClmx9Ynx3HenDXH1heTM7qg5Dff79csA&oe=6827D321",
            "https://scontent-mia3-2.xx.fbcdn.net/v/t39.30808-6/494807276_10236806443718131_650136072677716133_n.jpg?stp=dst-jpg_s960x960_tt6&_nc_cat=105&ccb=1-7&_nc_sid=946e27&_nc_ohc=EM1oAp_COeoQ7kNvwGZ0xdu&_nc_oc=Admtooa_uXBWsDKoPyj_uUIGao2Qf-2S0u8--rBD0CjgWAgvBcnJV9AkhDDU5xmCwAM&_nc_zt=23&_nc_ht=scontent-mia3-2.xx&_nc_gid=DsTKVZHDiKbqG7R2lPOUcg&oh=00_AfJGZlvmEA0powqSMXctD7QpdvI56XMKz9pKd0duF8lsPw&oe=6827F686",
            "https://scontent-mia3-2.xx.fbcdn.net/v/t39.30808-6/496005947_10236806443558127_8107969176673126772_n.jpg?stp=dst-jpg_s960x960_tt6&_nc_cat=107&ccb=1-7&_nc_sid=946e27&_nc_ohc=5LTZA0E1F_4Q7kNvwHkA7zT&_nc_oc=AdkRwTuO6wDr5sdwUhey3rjumtHEQkSYOMlkhVm2e2VjKvO0xj9rnHGVyEWPU8MFjd0&_nc_zt=23&_nc_ht=scontent-mia3-2.xx&_nc_gid=DsTKVZHDiKbqG7R2lPOUcg&oh=00_AfKv71o3GmzR0BitOF7HblGJs6GXzQAGtCrjYVNMZI_3Yg&oe=6827EB1A"
        ]
    },
    "profile_info": {
        "profile_id": 1149471014,
        "profile_name": "Jeremie Egiazarian",
        "is_dealership": false,
        "lives_in": "N/A",
        "joined_facebook_in": 2008,
        "car_listings": 1,
        "rating": "N/A",
        "ratings_number": "N/A",
        "profile_link": "https://www.facebook.com/marketplace/profile/1149471014/"
    }
}