{
    "date": "2025-05-12",
    "product_title": "2010 Chevrolet traverse LT Sport Utility 4D",
    "product_price": 1100,
    "vehicle_info": {
        "mileage": 150000,
        "fuel_type": "Gasoline",
        "interior_color": "Grey",
        "exterior_color": "Silver",
        "consumption": {
            "city": 16.0,
            "highway": 23.0
        },
        "title": "Clean"
    },
    "publication_info": {
        "publication_id": 686664437284008,
        "publication_date": "2025-05-12",
        "product_title": "2010 Chevrolet traverse LT Sport Utility 4D",
        "product_price": 1100,
        "publication_description": "PRECIO FIRME \nNECESITA HACER EL TIEMPO DEL MOTOR SUENAN LAS CADENAS\nTITULO LIMPIO EN MANO  ",
        "publication_link": "https://www.facebook.com/marketplace/item/686664437284008/",
        "publication_location": "Hialeah, FL",
        "images": [
            "https://scontent-mia3-3.xx.fbcdn.net/v/t39.30808-6/496940163_736163978985306_8387127413843500326_n.jpg?stp=dst-jpg_s960x960_tt6&_nc_cat=109&ccb=1-7&_nc_sid=454cf4&_nc_ohc=i7qcn3lT-BEQ7kNvwEGlqcl&_nc_oc=Adn5RQvW9xLRVHldvTPvPiO94S-DuP3x9L6mcswWkOBbLdeP4QJgrpdD74nwLmI1oog&_nc_zt=23&_nc_ht=scontent-mia3-3.xx&_nc_gid=cV_x2FpzV_hFeceKda0IBA&oh=00_AfLrX0RsTOi6Cb-y9BcN6NkYAI644KhmdU92h6TnaNO4kQ&oe=6827DB08",
            "https://scontent-mia3-3.xx.fbcdn.net/v/t39.30808-6/496940163_736163978985306_8387127413843500326_n.jpg?stp=dst-jpg_s960x960_tt6&_nc_cat=109&ccb=1-7&_nc_sid=454cf4&_nc_ohc=i7qcn3lT-BEQ7kNvwEGlqcl&_nc_oc=Adn5RQvW9xLRVHldvTPvPiO94S-DuP3x9L6mcswWkOBbLdeP4QJgrpdD74nwLmI1oog&_nc_zt=23&_nc_ht=scontent-mia3-3.xx&_nc_gid=cV_x2FpzV_hFeceKda0IBA&oh=00_AfLrX0RsTOi6Cb-y9BcN6NkYAI644KhmdU92h6TnaNO4kQ&oe=6827DB08",
            "https://scontent-mia3-1.xx.fbcdn.net/v/t39.30808-6/496937715_736161842318853_3637203520709062097_n.jpg?stp=cp6_dst-jpg_s960x960_tt6&_nc_cat=106&ccb=1-7&_nc_sid=946e27&_nc_ohc=w_vQKCbwX3YQ7kNvwEIIuBg&_nc_oc=Adm3oyuSnYA6L055cKmuDhKoV1a9vYq-mRtBLSkdBGTuRkpvCS1YQ5jBD6WcDYBT5yw&_nc_zt=23&_nc_ht=scontent-mia3-1.xx&_nc_gid=cV_x2FpzV_hFeceKda0IBA&oh=00_AfLNxi0ZhPzeuzYxQs5PTFDGNMvYX1f51w71Nm2hDQtNug&oe=6827B27B"
        ]
    },
    "profile_info": {
        "profile_id": 100077751325485,
        "profile_name": "N/A",
        "is_dealership": false,
        "lives_in": "N/A",
        "joined_facebook_in": "N/A",
        "car_listings": 0,
        "rating": "N/A",
        "ratings_number": "N/A",
        "profile_link": "https://www.facebook.com/marketplace/profile/100077751325485/"
    }
}