{
    "date": "2025-05-11",
    "product_title": "2015 Ford mustang Coupe 2D",
    "product_price": 19888,
    "vehicle_info": {
        "mileage": 100000,
        "fuel_type": "Gasoline",
        "interior_color": "Black",
        "exterior_color": "Blue",
        "title": "Clean"
    },
    "publication_info": {
        "publication_id": 1045516740327174,
        "publication_date": "2025-05-11",
        "product_title": "2015 Ford mustang Coupe 2D",
        "product_price": 19888,
        "publication_description": "Ford Mustang 2015 \u2013 Azul El\u00e9ctrico, Pura Potencia en Transmisi\u00f3n Est\u00e1ndar\n\u00a1Para los que aman manejar de verdad!\n \u2022 100,000 millas\n \u2022 Transmisi\u00f3n manual (est\u00e1ndar), conexi\u00f3n total con el camino\n \u2022 Color azul deportivo, imposible pasar desapercibido\n \u2022 Interior en piel negra, elegante y con car\u00e1cter\n \u2022 Equipado con pantalla y sonido premium\n\nPrecio total: $19,888\u2705\nDown payment: $2,999\u2705 See less",
        "publication_link": "https://www.facebook.com/marketplace/item/1045516740327174/",
        "publication_location": "Houston, TX",
        "images": [
            "https://scontent-mia3-3.xx.fbcdn.net/v/t39.30808-6/495430828_122267818796027561_6102563634937297664_n.jpg?stp=dst-jpg_s960x960_tt6&_nc_cat=108&ccb=1-7&_nc_sid=454cf4&_nc_ohc=iPb04yDkExkQ7kNvwFCMvAF&_nc_oc=Adl5SSYbZs9w7zuaYZeSnz-3od_MCPiMTOxmbtQoJm3nLczeUQoqK4liAh2Uzqk9-qw&_nc_zt=23&_nc_ht=scontent-mia3-3.xx&_nc_gid=e1uXBhisPDFsC11lko6ljQ&oh=00_AfK6zyaC0VDlSiyV48M328q6IaWlMvlFOCvJF-VvJLQJcA&oe=6827E5B4",
            "https://scontent-mia3-3.xx.fbcdn.net/v/t39.30808-6/495430828_122267818796027561_6102563634937297664_n.jpg?stp=dst-jpg_s960x960_tt6&_nc_cat=108&ccb=1-7&_nc_sid=454cf4&_nc_ohc=iPb04yDkExkQ7kNvwFCMvAF&_nc_oc=Adl5SSYbZs9w7zuaYZeSnz-3od_MCPiMTOxmbtQoJm3nLczeUQoqK4liAh2Uzqk9-qw&_nc_zt=23&_nc_ht=scontent-mia3-3.xx&_nc_gid=e1uXBhisPDFsC11lko6ljQ&oh=00_AfK6zyaC0VDlSiyV48M328q6IaWlMvlFOCvJF-VvJLQJcA&oe=6827E5B4",
            "https://scontent-mia3-1.xx.fbcdn.net/v/t39.30808-6/495546641_122267816222027561_7874721368785810375_n.jpg?stp=dst-jpg_s960x960_tt6&_nc_cat=106&ccb=1-7&_nc_sid=946e27&_nc_ohc=jE1k3lgx0-AQ7kNvwHUdHf5&_nc_oc=AdlSJetGneWNZgKIc6hxUpe0h2aRxH94wRrh7SghHNHmNICRRl8l4H0ipCI9lEpM4rQ&_nc_zt=23&_nc_ht=scontent-mia3-1.xx&_nc_gid=e1uXBhisPDFsC11lko6ljQ&oh=00_AfIcbGs0WMvcdpJb6VSVOVvhh4DDWxDlgE88c3z9GNk9rA&oe=6827FBDA"
        ]
    },
    "profile_info": {
        "profile_id": 61550826843234,
        "profile_name": "Cristina Bianchi",
        "is_dealership": true,
        "lives_in": "Houston, Texas",
        "joined_facebook_in": 2023,
        "car_listings": 4,
        "rating": "N/A",
        "ratings_number": "N/A",
        "profile_link": "https://www.facebook.com/marketplace/profile/61550826843234/"
    }
}